django_buymeacoffee/__init__.py
django_buymeacoffee/admin.py
django_buymeacoffee/api.py
django_buymeacoffee/apps.py
django_buymeacoffee/models.py
django_buymeacoffee/tests.py
django_buymeacoffee/urls.py
django_buymeacoffee/views.py
django_buymeacoffee/docs/index.rst
django_buymeacoffee/migrations/__init__.py
django_buymeacoffee/tests/__init__.py
django_buymeacoffee/tests/test_webhooks.py
django_buymeacoffee-0.1.0.dist-info/LICENSE
django_buymeacoffee-0.1.0.dist-info/METADATA
django_buymeacoffee-0.1.0.dist-info/WHEEL
django_buymeacoffee-0.1.0.dist-info/top_level.txt
django_buymeacoffee-0.1.0.dist-info/RECORD
