Metadata-Version: 2.1
Name: django-buymeacoffee
Version: 0.1.0
Summary: "A Django app for integrating Buy Me a Coffee as a webhook endpoint to receive donations, purchases and subscription events."
Home-page: https://github.com/Qoyyuum/django-buymeacoffee
Author: "Abdul Qoyyuum bin Haji Abdul Kadir"
Author-email: "iam@programmerq.dev"
License: MIT
Classifier: Environment :: Web Environment
Classifier: Framework :: Django
Classifier: Framework :: Django :: 4.0
Classifier: Intended Audience :: Developers
Classifier: License :: OSI Approved :: MIT License
Classifier: Operating System :: OS Independent
Classifier: Programming Language :: Python
Classifier: Programming Language :: Python :: 3
Classifier: Programming Language :: Python :: 3.9
Classifier: Programming Language :: Python :: 3.10
Classifier: Programming Language :: Python :: 3 :: Only
Classifier: Topic :: Internet :: WWW/HTTP
Classifier: Topic :: Internet :: WWW/HTTP :: Dynamic Content
Requires-Python: >=3.9
License-File: LICENSE
Requires-Dist: django>=4.0
Requires-Dist: django-ninja>=0.19
Requires-Dist: requests>=2.25
Provides-Extra: dev
Requires-Dist: black>=22.3; extra == "dev"
Requires-Dist: coverage>=6.3; extra == "dev"
Requires-Dist: django-debug-toolbar>=3.2; extra == "dev"
Requires-Dist: django-extensions>=3.1; extra == "dev"
Requires-Dist: django-jazzmin>=2.4; extra == "dev"
Requires-Dist: freezegun>=1.2; extra == "dev"
Requires-Dist: isort>=5.10; extra == "dev"
Requires-Dist: mock>=4.0; extra == "dev"
Requires-Dist: mypy>=0.910; extra == "dev"
Requires-Dist: pre-commit>=2.16; extra == "dev"
Requires-Dist: pytest>=6.2; extra == "dev"
Requires-Dist: pytest-cov>=3.0; extra == "dev"
Requires-Dist: pytest-django>=4.4; extra == "dev"
Requires-Dist: tox>=3.24; extra == "dev"
